signalprocessingforCM/__init__.py
signalprocessingforCM/signalprocessing.py
signalprocessingforcm-0.2.6.dist-info/METADATA
signalprocessingforcm-0.2.6.dist-info/WHEEL
signalprocessingforcm-0.2.6.dist-info/RECORD
