Metadata-Version: 2.1
Name: signalprocessingforCM
Version: 0.2.6
Summary: Signal Processing for Condition Monitoring for Mechanical Engineering and Vibration Based Condition Monitoring.
Author: Justin Smith
Author-email: 66smithjustin@gmail.com
Requires-Python: >=3.11,<3.12
Classifier: Programming Language :: Python :: 3
Classifier: Programming Language :: Python :: 3.11
Requires-Dist: black (>=24.8.0,<25.0.0)
Requires-Dist: ipykernel (>=6.29.5,<7.0.0)
Requires-Dist: matplotlib (>=3.9.2,<4.0.0)
Requires-Dist: numba (>=0.60.0,<0.61.0)
Requires-Dist: numpy (>=1.2.0,<2.0.0)
Requires-Dist: pandas (>=2.2.2,<3.0.0)
Requires-Dist: scikit-learn (>=1.5.1,<2.0.0)
Requires-Dist: scipy (>=1.14.0,<2.0.0)
Requires-Dist: statistics (>=1.0.3.5,<2.0.0.0)
Requires-Dist: tables (>=3.10.0,<4.0.0)
